asyn_fifo.v


  `timescale 1ns/1ns

 module fifo(
	  input winc,wclk,wrst,
	  input rinc,rclk,rrst,
	  input  [7:0] wdata,
	  output [7:0] rdata,
	  output full,empty );

  wire [3:0]waddr,raddr;
  wire [4:0]rptr,wptr;

  fifomem fmem(
               .wdata(wdata),
	       .waddr(waddr),.raddr(raddr),
	       .winc(winc),.wclk(wclk),.full(full),.empty(empty),.rclk(rclk),.rinc(rinc),
	       .rdata(rdata) );


   write wr(.winc(winc),
	    .rptr(rptr),
	    .wfull(full),
	    .wclk(wclk), .wrst_n(wrst),
	    .waddr(waddr),
	    .wptr(wptr) );


     read rd(
	      .rinc(rinc),
	      .wptr(wptr),
	      .empty(empty),
	      .rclk(rclk), .rrst_n(rrst),
	      .raddr(raddr),
	      .rptr(rptr)  );

   endmodule




 module fifomem(
             input [7:0]wdata,
	     input [3:0]waddr,raddr,
	     input winc,wclk,full,empty,rclk,rinc,
	     output reg [7:0] rdata );
   
   reg [7:0] mem [0:15] ;
 


   //assign wclken = (!full & winc) ;  

   always @(posedge wclk) begin   
	   if(winc && !full) begin
                  mem[waddr] <= wdata;
                end  
           //if(rinc & !empty) begin
	//	   rdata <= mem[raddr] ;
	  // end
      end

      always @(posedge rclk) begin  
	      if(rinc & !empty) begin
		   rdata <= mem[raddr] ;
	   end
      end


  endmodule


   module write(
	    input winc,
	    input [4:0]rptr,
	    output reg wfull,
	    input wclk,wrst_n,
	    output [3:0]waddr,
	    output reg [4:0]wptr );

    reg [4:0]wbin;
    wire [4:0] wgnext;
    wire [4:0] wbnext;
    reg [4:0] wq1_rptr,wq2_rptr; 
    wire full;

   assign waddr = wbin[3:0];
   assign wbnext = wbin + (winc && (!wfull));

   
   assign full = ((wgnext[4] != wq2_rptr[4] ) && (wgnext[3] != wq2_rptr[3]) && (wgnext[2:0] == wq2_rptr[2:0]));

    always @(posedge wclk, negedge wrst_n) begin
	    if(!wrst_n) begin
               wbin <= 4'd0;
	       wptr <= 4'd0; end
	    else begin
	       wbin <= wbnext;
               wptr <= wgnext; end
       end

    assign  wgnext = {wbnext[4],(wbnext[4]^wbnext[3]), (wbnext[3]^wbnext[2]), (wbnext[2]^wbnext[1]),(wbnext[1]^wbnext[0])};

    always @(posedge wclk, negedge wrst_n)
	  begin
	    if(!wrst_n) 
	         {wq2_rptr,wq1_rptr} <= 8'd0;
            else
		 {wq2_rptr,wq1_rptr} <= {wq1_rptr,rptr};
          end

	  always @(posedge wclk, negedge wrst_n)
          begin
	   if(!wrst_n) 
	      wfull <= 1'b0;
	   else
	      wfull <= full;
          end

    endmodule
	     
   module read(
	    input rinc,
	    input [4:0]wptr,
	    output reg empty,
	    input rclk,rrst_n,
	    output [3:0]raddr,
	    output reg [4:0]rptr  );
    
    wire rempty;
    reg [4:0]rbin;
    wire [4:0] rgnext;
    reg [4:0]rq2_wptr,rq1_wptr;
    wire [4:0]rbnext;

    always @(posedge rclk, negedge rrst_n)
	  begin
	    if(!rrst_n) 
	         {rq2_wptr,rq1_wptr} <= 8'd0;
            else
		 {rq2_wptr,rq1_wptr} <= {rq1_wptr,wptr};

          end

     always @(posedge rclk, negedge rrst_n) begin
	    if(!rrst_n) begin
              rbin <= 4'd0;
	      rptr <= 4'd0; end
	    else begin
	      rbin <= rbnext;
              rptr <= rgnext; end
       end 


    assign raddr = rbin[3:0];
    assign rbnext = rbin + (rinc && (!empty));
    assign rgnext = {rbnext[4],(rbnext[4]^rbnext[3]), (rbnext[3]^rbnext[2]), (rbnext[2]^rbnext[1]),(rbnext[1]^rbnext[0])};
     
   assign  rempty = (rq2_wptr == rgnext);
  
   always @(posedge rclk, negedge rrst_n)
   begin
	   if(!rrst_n) 
	      empty <= 1'b1;
	   else
	      empty <= rempty;
    end
  endmodule

asyn_fifo_tb.v
// Code your testbench here
// or browse Examples



  module test;

  reg winc,wclk,wrst;
  reg rinc,rclk,rrst;
  reg [7:0] wdata;
  wire [7:0] rdata;
  wire empty,full;

  fifo dut(
	   .winc(winc),.wclk(wclk),.wrst(wrst),
	   .rinc(rinc),.rclk(rclk),.rrst(rrst),
	   .wdata(wdata),
	   .rdata(rdata),
	   .full(full),.empty(empty) );
  
  initial begin
   rclk =0;
   forever #4 rclk = ~rclk;
  end

  initial begin
   wclk =0;
   forever #5 wclk = ~wclk;
  end

  
  integer i,j;

  initial begin
  wrst = 0; rrst=0;  
  @(negedge wclk); wrst=1; rrst = 1; winc = 0; rinc = 0; 
 
    @(negedge wclk);
    for(i=0; i<20; i=i+1)
       begin winc = 1; 
          wdata = {$random};
             
             @(negedge wclk);
    end
    
    @(negedge wclk);
    @(negedge rclk);  winc=0; 
    for(j=0; j<20; j=j+1)
      begin rinc = 1;
            @(negedge rclk);
       end
    repeat(4) @(negedge rclk); $finish;
    end
  
 initial
 begin
 $dumpfile("asyn_fifo.vcd");
 $dumpvars;
 end

 endmodule

asyn_fifo.vcd
$date
	Sun Nov 28 19:52:26 2021
$end
$version
	Icarus Verilog
$end
$timescale
	1ns
$end
$scope module test $end
$var wire 8 ! rdata [7:0] $end
$var wire 1 " full $end
$var wire 1 # empty $end
$var reg 1 $ rclk $end
$var reg 1 % rinc $end
$var reg 1 & rrst $end
$var reg 1 ' wclk $end
$var reg 8 ( wdata [7:0] $end
$var reg 1 ) winc $end
$var reg 1 * wrst $end
$var integer 32 + i [31:0] $end
$var integer 32 , j [31:0] $end
$scope module dut $end
$var wire 1 $ rclk $end
$var wire 1 % rinc $end
$var wire 1 & rrst $end
$var wire 1 ' wclk $end
$var wire 8 - wdata [7:0] $end
$var wire 1 ) winc $end
$var wire 1 * wrst $end
$var wire 5 . wptr [4:0] $end
$var wire 4 / waddr [3:0] $end
$var wire 5 0 rptr [4:0] $end
$var wire 8 1 rdata [7:0] $end
$var wire 4 2 raddr [3:0] $end
$var wire 1 " full $end
$var wire 1 # empty $end
$scope module fmem $end
$var wire 1 $ rclk $end
$var wire 1 % rinc $end
$var wire 1 ' wclk $end
$var wire 8 3 wdata [7:0] $end
$var wire 1 ) winc $end
$var wire 4 4 waddr [3:0] $end
$var wire 4 5 raddr [3:0] $end
$var wire 1 " full $end
$var wire 1 # empty $end
$var reg 8 6 rdata [7:0] $end
$upscope $end
$scope module rd $end
$var wire 1 $ rclk $end
$var wire 1 % rinc $end
$var wire 1 & rrst_n $end
$var wire 5 7 wptr [4:0] $end
$var wire 5 8 rgnext [4:0] $end
$var wire 1 9 rempty $end
$var wire 5 : rbnext [4:0] $end
$var wire 4 ; raddr [3:0] $end
$var reg 1 # empty $end
$var reg 5 < rbin [4:0] $end
$var reg 5 = rptr [4:0] $end
$var reg 5 > rq1_wptr [4:0] $end
$var reg 5 ? rq2_wptr [4:0] $end
$upscope $end
$scope module wr $end
$var wire 1 @ full $end
$var wire 5 A rptr [4:0] $end
$var wire 1 ' wclk $end
$var wire 1 ) winc $end
$var wire 1 * wrst_n $end
$var wire 5 B wgnext [4:0] $end
$var wire 5 C wbnext [4:0] $end
$var wire 4 D waddr [3:0] $end
$var reg 5 E wbin [4:0] $end
$var reg 1 " wfull $end
$var reg 5 F wptr [4:0] $end
$var reg 5 G wq1_rptr [4:0] $end
$var reg 5 H wq2_rptr [4:0] $end
$upscope $end
$upscope $end
$upscope $end
$enddefinitions $end
#0
$dumpvars
b0 H
b0 G
b0 F
b0 E
b0 D
bx C
bx B
b0 A
x@
b0 ?
b0 >
b0 =
b0 <
b0 ;
b0 :
19
b0 8
b0 7
bx 6
b0 5
b0 4
bx 3
b0 2
bx 1
b0 0
b0 /
b0 .
bx -
bx ,
bx +
0*
x)
bx (
0'
0&
x%
0$
1#
0"
bx !
$end
#4
1$
#5
1'
#8
0$
#10
0@
b0 B
b0 C
0%
0)
1&
1*
0'
#12
1$
#15
1'
#16
0$
#20
b1 B
b1 C
b100100 (
b100100 -
b100100 3
1)
b0 +
1$
0'
#24
0$
#25
b11 B
b1 /
b1 4
b1 D
b1 .
b1 7
b1 F
b10 C
b1 E
1'
#28
b1 >
1$
#30
b10000001 (
b10000001 -
b10000001 3
b1 +
0'
#32
0$
#35
b10 B
b10 /
b10 4
b10 D
b11 .
b11 7
b11 F
b11 C
b10 E
1'
#36
09
b1 ?
b11 >
1$
#40
b1001 (
b1001 -
b1001 3
b10 +
0$
0'
#44
b11 ?
0#
1$
#45
b110 B
b11 /
b11 4
b11 D
b10 .
b10 7
b10 F
b100 C
b11 E
1'
#48
0$
#50
b1100011 (
b1100011 -
b1100011 3
b11 +
0'
#52
b10 >
1$
#55
b111 B
b100 /
b100 4
b100 D
b110 .
b110 7
b110 F
b101 C
b100 E
1'
#56
0$
#60
b10 ?
b110 >
b1101 (
b1101 -
b1101 3
b100 +
1$
0'
#64
0$
#65
b101 B
b101 /
b101 4
b101 D
b111 .
b111 7
b111 F
b110 C
b101 E
1'
#68
b110 ?
b111 >
1$
#70
b10001101 (
b10001101 -
b10001101 3
b101 +
0'
#72
0$
#75
b100 B
b110 /
b110 4
b110 D
b101 .
b101 7
b101 F
b111 C
b110 E
1'
#76
b111 ?
b101 >
1$
#80
b1100101 (
b1100101 -
b1100101 3
b110 +
0$
0'
#84
b101 ?
1$
#85
b1100 B
b111 /
b111 4
b111 D
b100 .
b100 7
b100 F
b1000 C
b111 E
1'
#88
0$
#90
b10010 (
b10010 -
b10010 3
b111 +
0'
#92
b100 >
1$
#95
b1101 B
b1000 /
b1000 4
b1000 D
b1100 .
b1100 7
b1100 F
b1001 C
b1000 E
1'
#96
0$
#100
b100 ?
b1100 >
b1 (
b1 -
b1 3
b1000 +
1$
0'
#104
0$
#105
b1111 B
b1001 /
b1001 4
b1001 D
b1101 .
b1101 7
b1101 F
b1010 C
b1001 E
1'
#108
b1100 ?
b1101 >
1$
#110
b1101 (
b1101 -
b1101 3
b1001 +
0'
#112
0$
#115
b1110 B
b1010 /
b1010 4
b1010 D
b1111 .
b1111 7
b1111 F
b1011 C
b1010 E
1'
#116
b1101 ?
b1111 >
1$
#120
b1110110 (
b1110110 -
b1110110 3
b1010 +
0$
0'
#124
b1111 ?
1$
#125
b1010 B
b1011 /
b1011 4
b1011 D
b1110 .
b1110 7
b1110 F
b1100 C
b1011 E
1'
#128
0$
#130
b111101 (
b111101 -
b111101 3
b1011 +
0'
#132
b1110 >
1$
#135
b1011 B
b1100 /
b1100 4
b1100 D
b1010 .
b1010 7
b1010 F
b1101 C
b1100 E
1'
#136
0$
#140
b1110 ?
b1010 >
b11101101 (
b11101101 -
b11101101 3
b1100 +
1$
0'
#144
0$
#145
b1001 B
b1101 /
b1101 4
b1101 D
b1011 .
b1011 7
b1011 F
b1110 C
b1101 E
1'
#148
b1010 ?
b1011 >
1$
#150
b10001100 (
b10001100 -
b10001100 3
b1101 +
0'
#152
0$
#155
b1000 B
b1110 /
b1110 4
b1110 D
b1001 .
b1001 7
b1001 F
b1111 C
b1110 E
1'
#156
b1011 ?
b1001 >
1$
#160
b11111001 (
b11111001 -
b11111001 3
b1110 +
0$
0'
#164
b1001 ?
1$
#165
1@
b1111 /
b1111 4
b1111 D
b11000 B
b1000 .
b1000 7
b1000 F
b10000 C
b1111 E
1'
#168
0$
#170
b11000110 (
b11000110 -
b11000110 3
b1111 +
0'
#172
b1000 >
1$
#175
b0 /
b0 4
b0 D
b11000 .
b11000 7
b11000 F
b10000 C
b10000 E
1"
1'
#176
0$
#180
b1000 ?
b11000 >
b11000101 (
b11000101 -
b11000101 3
b10000 +
1$
0'
#184
0$
#185
1'
#188
b11000 ?
1$
#190
b10101010 (
b10101010 -
b10101010 3
b10001 +
0'
#192
0$
#195
1'
#196
1$
#200
b11100101 (
b11100101 -
b11100101 3
b10010 +
0$
0'
#204
1$
#205
1'
#208
0$
#210
b1110111 (
b1110111 -
b1110111 3
b10011 +
0'
#212
1$
#215
1'
#216
0$
#220
b10100 +
1$
0'
#224
0$
#225
1'
#228
1$
#230
0'
#232
b1 8
b1 :
1%
b0 ,
0)
0$
#235
1'
#236
b11 8
b1 2
b1 5
b1 ;
b100100 !
b100100 1
b100100 6
b1 0
b1 =
b1 A
b10 :
b1 <
1$
#240
b1 ,
0$
0'
#244
b10 8
b10 2
b10 5
b10 ;
b10000001 !
b10000001 1
b10000001 6
b11 0
b11 =
b11 A
b11 :
b10 <
1$
#245
b11 G
1'
#248
b10 ,
0$
#250
0'
#252
b110 8
b11 2
b11 5
b11 ;
b1001 !
b1001 1
b1001 6
b10 0
b10 =
b10 A
b100 :
b11 <
1$
#255
0@
b11 H
b10 G
1'
#256
b11 ,
0$
#260
b111 8
b100 2
b100 5
b100 ;
b1100011 !
b1100011 1
b1100011 6
b110 0
b110 =
b110 A
b101 :
b100 <
1$
0'
#264
b100 ,
0$
#265
0"
b10 H
b110 G
1'
#268
b101 8
b101 2
b101 5
b101 ;
b1101 !
b1101 1
b1101 6
b111 0
b111 =
b111 A
b110 :
b101 <
1$
#270
0'
#272
b101 ,
0$
#275
b110 H
b111 G
1'
#276
b100 8
b110 2
b110 5
b110 ;
b10001101 !
b10001101 1
b10001101 6
b101 0
b101 =
b101 A
b111 :
b110 <
1$
#280
b110 ,
0$
0'
#284
b1100 8
b111 2
b111 5
b111 ;
b1100101 !
b1100101 1
b1100101 6
b100 0
b100 =
b100 A
b1000 :
b111 <
1$
#285
b111 H
b100 G
1'
#288
b111 ,
0$
#290
0'
#292
b1101 8
b1000 2
b1000 5
b1000 ;
b10010 !
b10010 1
b10010 6
b1100 0
b1100 =
b1100 A
b1001 :
b1000 <
1$
#295
b100 H
b1100 G
1'
#296
b1000 ,
0$
#300
b1111 8
b1001 2
b1001 5
b1001 ;
b1 !
b1 1
b1 6
b1101 0
b1101 =
b1101 A
b1010 :
b1001 <
1$
0'
#304
b1001 ,
0$
#305
b1100 H
b1101 G
1'
#308
b1110 8
b1010 2
b1010 5
b1010 ;
b1101 !
b1101 1
b1101 6
b1111 0
b1111 =
b1111 A
b1011 :
b1010 <
1$
#310
0'
#312
b1010 ,
0$
#315
b1101 H
b1111 G
1'
#316
b1010 8
b1011 2
b1011 5
b1011 ;
b1110110 !
b1110110 1
b1110110 6
b1110 0
b1110 =
b1110 A
b1100 :
b1011 <
1$
#320
b1011 ,
0$
0'
#324
b1011 8
b1100 2
b1100 5
b1100 ;
b111101 !
b111101 1
b111101 6
b1010 0
b1010 =
b1010 A
b1101 :
b1100 <
1$
#325
b1111 H
b1010 G
1'
#328
b1100 ,
0$
#330
0'
#332
b1001 8
b1101 2
b1101 5
b1101 ;
b11101101 !
b11101101 1
b11101101 6
b1011 0
b1011 =
b1011 A
b1110 :
b1101 <
1$
#335
b1010 H
b1011 G
1'
#336
b1101 ,
0$
#340
b1000 8
b1110 2
b1110 5
b1110 ;
b10001100 !
b10001100 1
b10001100 6
b1001 0
b1001 =
b1001 A
b1111 :
b1110 <
1$
0'
#344
b1110 ,
0$
#345
b1011 H
b1001 G
1'
#348
b1111 2
b1111 5
b1111 ;
19
b11000 8
b11111001 !
b11111001 1
b11111001 6
b1000 0
b1000 =
b1000 A
b10000 :
b1111 <
1$
#350
0'
#352
b1111 ,
0$
#355
b1001 H
b1000 G
1'
#356
19
b11000 8
b0 2
b0 5
b0 ;
b11000110 !
b11000110 1
b11000110 6
1#
b11000 0
b11000 =
b11000 A
b10000 :
b10000 <
1$
#360
b10000 ,
0$
0'
#364
1$
#365
b1000 H
b11000 G
1'
#368
b10001 ,
0$
#370
0'
#372
1$
#375
b11000 H
1'
#376
b10010 ,
0$
#380
1$
0'
#384
b10011 ,
0$
#385
1'
#388
1$
#390
0'
#392
b10100 ,
0$
